LICENSE
README.md
setup.py
uni_active/__init__.py
uni_active.egg-info/PKG-INFO
uni_active.egg-info/SOURCES.txt
uni_active.egg-info/dependency_links.txt
uni_active.egg-info/requires.txt
uni_active.egg-info/top_level.txt
uni_active/cli/__init__.py
uni_active/data/__init__.py
uni_active/data/dataset.py
uni_active/feature/__init__.py
uni_active/grid/__init__.py
uni_active/grid/grid.py
uni_active/loop/__init__.py
uni_active/loop/loop.py
uni_active/model/__init__.py
uni_active/model/base.py
uni_active/model/func.py
uni_active/model/metrics.py
uni_active/selection/__init__.py
uni_active/selection/select.py
uni_active/utils/__init__.py
uni_active/utils/file_io.py
uni_active/utils/log.py