Metadata-Version: 2.1
Name: uni-active
Version: 0.0.2
Summary: machine learning
Home-page: https://git.dp.tech/ai/zw_project
Author: dp
Author-email: wangchangxin@dp.tech
License: LGPLv3
Keywords: Active Learning,selection
Platform: Windows
Platform: Unix
Classifier: Development Status :: 4 - Beta
Classifier: Intended Audience :: Science/Research
Classifier: License :: OSI Approved :: GNU General Public License v3 (GPLv3)
Classifier: Natural Language :: English
Classifier: Operating System :: Microsoft :: Windows
Classifier: Operating System :: Unix
Classifier: Programming Language :: Python :: 3.8
Classifier: Programming Language :: Python :: 3.9
Classifier: Programming Language :: Python :: 3.10
Classifier: Programming Language :: Python :: 3.11
Requires-Python: >=3.8
License-File: LICENSE
